{
  "/_not-found": "app/_not-found.js",
  "/favicon.ico/route": "app/favicon.ico/route.js",
  "/(Home)/page": "app/(Home)/page.js",
  "/(dashboard)/dashboard/contactUs/page": "app/(dashboard)/dashboard/contactUs/page.js",
  "/(dashboard)/dashboard/comments/page": "app/(dashboard)/dashboard/comments/page.js",
  "/(dashboard)/dashboard/jobs/page": "app/(dashboard)/dashboard/jobs/page.js",
  "/(dashboard)/dashboard/projects/[id]/edit/page": "app/(dashboard)/dashboard/projects/[id]/edit/page.js",
  "/(dashboard)/dashboard/team/[id]/page": "app/(dashboard)/dashboard/team/[id]/page.js",
  "/(dashboard)/dashboard/projects/page": "app/(dashboard)/dashboard/projects/page.js",
  "/(dashboard)/dashboard/orders/[id]/page": "app/(dashboard)/dashboard/orders/[id]/page.js",
  "/(dashboard)/dashboard/team/newEmplyee/page": "app/(dashboard)/dashboard/team/newEmplyee/page.js",
  "/(dashboard)/dashboard/team/page": "app/(dashboard)/dashboard/team/page.js",
  "/(dashboard)/dashboard/team/[id]/edit/page": "app/(dashboard)/dashboard/team/[id]/edit/page.js",
  "/(dashboard)/dashboard/orders/page": "app/(dashboard)/dashboard/orders/page.js",
  "/(dashboard)/dashboard/projects/[id]/page": "app/(dashboard)/dashboard/projects/[id]/page.js",
  "/(dashboard)/dashboard/users/page": "app/(dashboard)/dashboard/users/page.js",
  "/(dashboard)/dashboard/page": "app/(dashboard)/dashboard/page.js",
  "/(user)/user/login/page": "app/(user)/user/login/page.js",
  "/(user)/user/restPassword/page": "app/(user)/user/restPassword/page.js",
  "/(user)/user/page": "app/(user)/user/page.js",
  "/(user)/user/formRestPassword/page": "app/(user)/user/formRestPassword/page.js",
  "/(user)/user/Register/page": "app/(user)/user/Register/page.js",
  "/(Home)/jobs/page": "app/(Home)/jobs/page.js",
  "/(Home)/team/page": "app/(Home)/team/page.js",
  "/(Home)/myprojects/page": "app/(Home)/myprojects/page.js",
  "/(Home)/contact/page": "app/(Home)/contact/page.js",
  "/(Home)/order/page": "app/(Home)/order/page.js"
}